cj_package/__init__.py
cj_package/__version__.py
cj_package/aliyun.py
cj_package/command.py
cj_package/domain.py
cj_package/email.py
cj_package/excel.py
cj_package/qw.py
cj_package/sql.py
cj_package/time.py
cj_package/utils.py
cj_package/version.py
cj_package-1.0.50.dist-info/LICENSE
cj_package-1.0.50.dist-info/METADATA
cj_package-1.0.50.dist-info/WHEEL
cj_package-1.0.50.dist-info/top_level.txt
cj_package-1.0.50.dist-info/RECORD
