Metadata-Version: 2.1
Name: cj_package
Version: 1.0.50
Summary: cj package.
Author: chenxing
Author-email: chenxing@cjdropshipping.co
Classifier: Programming Language :: Python :: 3
Classifier: License :: OSI Approved :: MIT License
Classifier: Operating System :: OS Independent
Requires-Python: >=3
License-File: LICENSE
Requires-Dist: aliyun-log-python-sdk >=0.8.15
Requires-Dist: requests >=2.31.0
Requires-Dist: loguru >=0.6.0
Requires-Dist: dnspython
Requires-Dist: pandas
Requires-Dist: pendulum
Requires-Dist: pymysql
Requires-Dist: openpyxl
Requires-Dist: cryptography
Requires-Dist: yagmail
Requires-Dist: tqdm
Requires-Dist: pyperclip
Requires-Dist: emoji
